README.md
pystdin.py
setup.py
pystdin.egg-info/PKG-INFO
pystdin.egg-info/SOURCES.txt
pystdin.egg-info/dependency_links.txt
pystdin.egg-info/requires.txt
pystdin.egg-info/top_level.txt