Metadata-Version: 2.1
Name: pystdin
Version: 1.0.4
Summary: Wrap command-line Python code in a loop over standard input.
Home-page: https://github.com/terrycojones/pystdin
Author: Terry Jones
Author-email: tcj25@cam.ac.uk
License: MIT
Download-URL: https://github.com/terrycojones/pystdin
Keywords: python stdin standard input
Platform: UNKNOWN
Classifier: Programming Language :: Python :: 2.7
Classifier: Programming Language :: Python :: 3
Classifier: Development Status :: 4 - Beta
Classifier: Intended Audience :: Developers
Classifier: License :: OSI Approved :: MIT License
Classifier: Operating System :: OS Independent
Classifier: Topic :: Software Development :: Libraries :: Python Modules
Provides-Extra: dev
